[
  {
    "description": "  BAR-TH-101 - chauffe eau solaire individuel",
    "keyword": "Feature",
    "name": "Simulation sur l OS BAR-TH-101",
    "line": 1,
    "id": "simulation-sur-l-os-bar-th-101",
    "tags": [],
    "uri": "SimulationBAR-TH-101.feature",
    "elements": [
      {
        "id": "simulation-sur-l-os-bar-th-101;connexion-au-bo",
        "keyword": "Scenario",
        "line": 7,
        "name": "Connexion au BO",
        "tags": [
          {
            "name": "@Simulateur",
            "line": 5
          },
          {
            "name": "@focus",
            "line": 6
          }
        ],
        "type": "scenario",
        "steps": [
          {
            "arguments": [],
            "keyword": "Given ",
            "line": 8,
            "name": "Je me suis connecte au BO",
            "result": {
              "status": "passed",
              "duration": 4363000000
            }
          }
        ]
      },
      {
        "id": "simulation-sur-l-os-bar-th-101;simulation-sur-l-os-bar-th-101-en-zone-h1,-energie-n/a,-cdp-n/a-et-revenus-précaire-énergétique",
        "keyword": "Scenario",
        "line": 16,
        "name": "Simulation sur l OS BAR-TH-101 en zone H1, Energie N/A, CDP N/A et Revenus Précaire énergétique",
        "tags": [
          {
            "name": "@Simulateur",
            "line": 9
          },
          {
            "name": "@focus",
            "line": 10
          }
        ],
        "type": "scenario",
        "steps": [
          {
            "arguments": [],
            "keyword": "When ",
            "line": 12,
            "name": "Redirection Simulateur",
            "result": {
              "status": "passed",
              "duration": 1591000000
            }
          },
          {
            "arguments": [],
            "keyword": "Then ",
            "line": 13,
            "name": "Simulation sur l OS \"BAR-TH-101 - chauffe eau solaire individuel\"\"H1\"\"N/A\"\"N/A\"\"Précaire énergétique\"\"\"\"\"\"\"\"\"\"\"",
            "result": {
              "status": "passed",
              "duration": 5714000000
            }
          }
        ]
      },
      {
        "id": "simulation-sur-l-os-bar-th-101;simulation-sur-l-os-bar-th-101-en-zone-h2,-energie-n/a,-cdp-n/a-et-revenus-modeste",
        "keyword": "Scenario",
        "line": 17,
        "name": "Simulation sur l OS BAR-TH-101 en zone H2, Energie N/A, CDP N/A et Revenus Modeste",
        "tags": [
          {
            "name": "@Simulateur",
            "line": 9
          },
          {
            "name": "@focus",
            "line": 10
          }
        ],
        "type": "scenario",
        "steps": [
          {
            "arguments": [],
            "keyword": "When ",
            "line": 12,
            "name": "Redirection Simulateur",
            "result": {
              "status": "passed",
              "duration": 1556000000
            }
          },
          {
            "arguments": [],
            "keyword": "Then ",
            "line": 13,
            "name": "Simulation sur l OS \"BAR-TH-101 - chauffe eau solaire individuel\"\"H2\"\"N/A\"\"N/A\"\"Modeste\"\"\"\"\"\"\"\"\"\"\"",
            "result": {
              "status": "passed",
              "duration": 5638000000
            }
          }
        ]
      },
      {
        "id": "simulation-sur-l-os-bar-th-101;simulation-sur-l-os-bar-th-101-en-zone-h3,-energie-n/a,-cdp-n/a-et-revenus-standard",
        "keyword": "Scenario",
        "line": 18,
        "name": "Simulation sur l OS BAR-TH-101 en zone H3, Energie N/A, CDP N/A et Revenus Standard",
        "tags": [
          {
            "name": "@Simulateur",
            "line": 9
          },
          {
            "name": "@focus",
            "line": 10
          }
        ],
        "type": "scenario",
        "steps": [
          {
            "arguments": [],
            "keyword": "When ",
            "line": 12,
            "name": "Redirection Simulateur",
            "result": {
              "status": "passed",
              "duration": 1587000000
            }
          },
          {
            "arguments": [],
            "keyword": "Then ",
            "line": 13,
            "name": "Simulation sur l OS \"BAR-TH-101 - chauffe eau solaire individuel\"\"H3\"\"N/A\"\"N/A\"\"Standard\"\"\"\"\"\"\"\"\"\"\"",
            "result": {
              "status": "passed",
              "duration": 5645000000
            }
          }
        ]
      }
    ]
  }
]